elefantolib_fastapi/__init__.py
elefantolib_fastapi/connection.py
elefantolib_fastapi/depends.py
elefantolib_fastapi/exceptions.py
elefantolib_fastapi/pagination.py
elefantolib_fastapi/requests.py
elefantolib_fastapi/routes.py
elefantolib_fastapi/schemas.py
elefantolib_fastapi-0.9.2.dist-info/WHEEL
elefantolib_fastapi-0.9.2.dist-info/METADATA
elefantolib_fastapi-0.9.2.dist-info/RECORD
