Metadata-Version: 2.1
Name: elefantolib-fastapi
Version: 0.9.2
Summary: 
Author: gglassota
Author-email: gglassota2@gmail.com
Requires-Python: >=3.10,<4.0
Classifier: Programming Language :: Python :: 3
Classifier: Programming Language :: Python :: 3.10
Classifier: Programming Language :: Python :: 3.11
Requires-Dist: elefantolib (>=0.12.1,<0.13.0)
Requires-Dist: fastapi (>=0.104.0,<0.105.0)
Requires-Dist: pydantic (>=2.4.2,<3.0.0)
Requires-Dist: redis (>=5.0.1,<6.0.0)
Requires-Dist: sqlalchemy (>=2.0.22,<3.0.0)
